.gitignore
LICENSE.txt
MANIFEST.in
Pipfile-dist.m4
Pipfile.m4
README.rst
VERSION.txt
pyproject.toml
pyproject.toml.m4
requirements.txt.m4
setup.cfg
setup.cfg.m4
setup.py
tox.ini
bin/math-readline
bin/sage
bin/sage-cachegrind
bin/sage-callgrind
bin/sage-cleaner
bin/sage-coverage
bin/sage-cython
bin/sage-env
bin/sage-env-config.in
bin/sage-eval
bin/sage-fixdoctests
bin/sage-grep
bin/sage-grepdoc
bin/sage-inline-fortran
bin/sage-ipynb2rst
bin/sage-ipython
bin/sage-list-packages
bin/sage-massif
bin/sage-notebook
bin/sage-num-threads.py
bin/sage-omega
bin/sage-preparse
bin/sage-python
bin/sage-rebase.bat
bin/sage-rebase.sh
bin/sage-rebaseall.bat
bin/sage-rebaseall.sh
bin/sage-run
bin/sage-run-cython
bin/sage-runtests
bin/sage-src-env-config.in
bin/sage-startuptime.py
bin/sage-update-version
bin/sage-valgrind
bin/sage-venv-config
bin/sage-version.sh
sage/all.py
sage/all__sagemath_categories.py
sage/all__sagemath_environment.py
sage/all__sagemath_objects.py
sage/all__sagemath_repl.py
sage/all_cmdline.py
sage/env.py
sage/version.py
sage/algebras/affine_nil_temperley_lieb.py
sage/algebras/algebra.py
sage/algebras/all.py
sage/algebras/askey_wilson.py
sage/algebras/associated_graded.py
sage/algebras/catalog.py
sage/algebras/cellular_basis.py
sage/algebras/clifford_algebra.py
sage/algebras/clifford_algebra_element.pxd
sage/algebras/clifford_algebra_element.pyx
sage/algebras/cluster_algebra.py
sage/algebras/commutative_dga.py
sage/algebras/down_up_algebra.py
sage/algebras/exterior_algebra_groebner.pxd
sage/algebras/exterior_algebra_groebner.pyx
sage/algebras/finite_gca.py
sage/algebras/free_algebra.py
sage/algebras/free_algebra_element.py
sage/algebras/free_algebra_quotient.py
sage/algebras/free_algebra_quotient_element.py
sage/algebras/free_zinbiel_algebra.py
sage/algebras/group_algebra.py
sage/algebras/hall_algebra.py
sage/algebras/iwahori_hecke_algebra.py
sage/algebras/jordan_algebra.py
sage/algebras/nil_coxeter_algebra.py
sage/algebras/octonion_algebra.pxd
sagemath_standard.egg-info/PKG-INFO
sagemath_standard.egg-info/SOURCES.txt
sagemath_standard.egg-info/dependency_links.txt
sagemath_standard.egg-info/requires.txt
sagemath_standard.egg-info/top_level.txt