Metadata-Version: 2.1
Name: sagemath-standard
Version: 10.2
Summary: Sage: Open Source Mathematics Software: Standard Python Library
Home-page: https://www.sagemath.org
Author: The Sage Developers
Author-email: sage-support@googlegroups.com
License: GNU General Public License (GPL) v2 or later
Classifier: Development Status :: 6 - Mature
Classifier: Intended Audience :: Education
Classifier: Intended Audience :: Science/Research
Classifier: License :: OSI Approved :: GNU General Public License v2 or later (GPLv2+)
Classifier: Operating System :: POSIX
Classifier: Operating System :: MacOS :: MacOS X
Classifier: Programming Language :: Python :: 3 :: Only
Classifier: Programming Language :: Python :: 3.9
Classifier: Programming Language :: Python :: 3.10
Classifier: Programming Language :: Python :: 3.11
Classifier: Programming Language :: Python :: Implementation :: CPython
Classifier: Topic :: Scientific/Engineering :: Mathematics
Requires-Python: <3.12,>=3.9
License-File: LICENSE.txt
Requires-Dist: sage-conf~=10.2
Requires-Dist: six>=1.15.0
Requires-Dist: cypari2>=2.1.1
Requires-Dist: cysignals>=1.10.2
Requires-Dist: cython!=3.0.3,<4.0,>=3.0
Requires-Dist: gmpy2>=2.1.0
Requires-Dist: importlib_metadata>=4.13
Requires-Dist: importlib_resources>=5.7
Requires-Dist: jupyter_core>=4.6.3
Requires-Dist: lrcalc~=2.1
Requires-Dist: memory_allocator
Requires-Dist: numpy>=1.19
Requires-Dist: pkgconfig
Requires-Dist: pplpy>=0.8.6
Requires-Dist: primecountpy
Requires-Dist: requests>=2.13.0
Requires-Dist: typing_extensions>=4.4.0
Requires-Dist: ipython<8.9.0,>=7.13.0
Requires-Dist: pexpect>=4.8.0
Requires-Dist: sphinx<8,>=5.2
Requires-Dist: networkx<3.3,>=2.4
Requires-Dist: scipy<1.12,>=1.5
Requires-Dist: sympy<2.0,>=1.6
Requires-Dist: matplotlib>=3.5.1
Requires-Dist: pillow>=7.2.0
Requires-Dist: mpmath>=1.1.0
Requires-Dist: ipykernel>=5.2.1
Requires-Dist: jupyter_client>=6.1.6
Requires-Dist: ipywidgets>=7.5.1
Requires-Dist: fpylll>=0.5.9
Requires-Dist: ptyprocess>0.5
Provides-Extra: r
Requires-Dist: rpy2>=3.3; extra == "r"
